httpxfetch/__init__.py
httpxfetch-0.0.2.dist-info/LICENSE
httpxfetch-0.0.2.dist-info/METADATA
httpxfetch-0.0.2.dist-info/WHEEL
httpxfetch-0.0.2.dist-info/top_level.txt
httpxfetch-0.0.2.dist-info/RECORD
