Metadata-Version: 2.1
Name: httpxfetch
Version: 0.0.2
Summary: httpxfetch is a Python wrapper for the JavaScript fetch function, designed to streamline the process of reverse engineering APIs.
Author-email: Adaías Magdiel <eu@adaiasmagdiel.com>
Project-URL: Homepage, https://github.com/AdaiasMagdiel/httpxfetch
Project-URL: Issues, https://github.com/AdaiasMagdiel/httpxfetch/issues
Keywords: fetch,httpx,reverse engineering,JavaScript
Classifier: Intended Audience :: Developers
Classifier: Programming Language :: Python :: 3
Classifier: Programming Language :: Python :: 3.6
Classifier: Programming Language :: Python :: 3.7
Classifier: Programming Language :: Python :: 3.8
Classifier: Programming Language :: Python :: 3.9
Classifier: Programming Language :: Python :: 3.10
Classifier: License :: OSI Approved :: MIT License
Classifier: Operating System :: OS Independent
Classifier: Topic :: Software Development :: Libraries :: Python Modules
Classifier: Topic :: Internet :: WWW/HTTP
Classifier: Topic :: Utilities
Requires-Python: >=3.6
License-File: LICENSE
Requires-Dist: httpx ==0.26.0
